{"cameraMode":{"drawMode":0,"name":"Shaded","section":"Shading Mode"},"sceneLighting":true,"audioPlay":false,"sceneViewState":{"m_AlwaysRefresh":false,"showFog":true,"showSkybox":true,"showFlares":true,"showImageEffects":true,"showParticleSystems":true,"showVisualEffectGraphs":true,"m_FxEnabled":true},"in2DMode":false,"pivot":{"x":2.4674930572509767,"y":2.339355707168579,"z":-7.223236560821533},"rotation":{"x":-0.22733303904533387,"y":0.06188425421714783,"z":-0.014477737247943879,"w":-0.971747100353241},"size":6.808413028717041,"orthographic":false}